odoo/addons/sale_crm_event_reservation/README.rst
odoo/addons/sale_crm_event_reservation/__init__.py
odoo/addons/sale_crm_event_reservation/__manifest__.py
odoo/addons/sale_crm_event_reservation/i18n/es.po
odoo/addons/sale_crm_event_reservation/i18n/sale_crm_event_reservation.pot
odoo/addons/sale_crm_event_reservation/readme/CONFIGURE.rst
odoo/addons/sale_crm_event_reservation/readme/CONTRIBUTORS.rst
odoo/addons/sale_crm_event_reservation/readme/DESCRIPTION.rst
odoo/addons/sale_crm_event_reservation/readme/INSTALL.rst
odoo/addons/sale_crm_event_reservation/readme/USAGE.rst
odoo/addons/sale_crm_event_reservation/reports/__init__.py
odoo/addons/sale_crm_event_reservation/reports/event_type_report.py
odoo/addons/sale_crm_event_reservation/reports/event_type_report_views.xml
odoo/addons/sale_crm_event_reservation/static/description/icon.png
odoo/addons/sale_crm_event_reservation/static/description/index.html
odoo/addons/sale_crm_event_reservation/tests/__init__.py
odoo/addons/sale_crm_event_reservation/tests/test_wizard.py
odoo/addons/sale_crm_event_reservation/views/crm_lead_views.xml
odoo/addons/sale_crm_event_reservation/wizards/__init__.py
odoo/addons/sale_crm_event_reservation/wizards/crm_lead_event_sale_wizard.py
odoo/addons/sale_crm_event_reservation/wizards/crm_lead_event_sale_wizard_views.xml
odoo13_addon_sale_crm_event_reservation-13.0.1.0.1.dist-info/METADATA
odoo13_addon_sale_crm_event_reservation-13.0.1.0.1.dist-info/WHEEL
odoo13_addon_sale_crm_event_reservation-13.0.1.0.1.dist-info/top_level.txt
odoo13_addon_sale_crm_event_reservation-13.0.1.0.1.dist-info/RECORD
